CHANGELOG.md
Cargo.toml
LICENSE-APACHE
LICENSE-MIT
README.md
fastloess/__init__.py
fastloess/__init__.pyi
fastloess/__version__.py
fastloess/fastloess.cpython-311-aarch64-linux-gnu.so
fastloess/py.typed
fastloess-0.1.0.dist-info/METADATA
fastloess-0.1.0.dist-info/WHEEL
fastloess-0.1.0.dist-info/licenses/LICENSE-APACHE
fastloess-0.1.0.dist-info/licenses/LICENSE-MIT
pyproject.toml
fastloess-0.1.0.dist-info/RECORD
