Metadata-Version: 2.4
Name: fastloess
Version: 0.1.0
Classifier: Development Status :: 5 - Production/Stable
Classifier: Intended Audience :: Science/Research
Classifier: License :: OSI Approved :: MIT License
Classifier: License :: OSI Approved :: Apache Software License
Classifier: Programming Language :: Rust
Classifier: Programming Language :: Python :: 3
Classifier: Programming Language :: Python :: 3.8
Classifier: Programming Language :: Python :: 3.9
Classifier: Programming Language :: Python :: 3.10
Classifier: Programming Language :: Python :: 3.11
Classifier: Programming Language :: Python :: 3.12
Classifier: Programming Language :: Python :: 3.13
Classifier: Programming Language :: Python :: 3.14
Classifier: Programming Language :: Python :: Implementation :: CPython
Classifier: Topic :: Scientific/Engineering :: Mathematics
Classifier: Topic :: Scientific/Engineering :: Information Analysis
Classifier: Operating System :: OS Independent
Requires-Dist: numpy>=1.20.0
License-File: LICENSE-APACHE
License-File: LICENSE-MIT
Summary: High-level, fast LOESS smoothing built on top of the fastLoess Rust crate.
Keywords: loess,smoothing,statistics,regression,numpy
Home-Page: https://github.com/thisisamirv/fastLoess-py
Author-email: Amir Valizadeh <thisisamirv@gmail.com>
License: MIT OR Apache-2.0
Requires-Python: >=3.8
